{
	"name": "tumblings_pipeline2",
	"properties": {
		"activities": [
			{
				"name": "Copy data1",
				"type": "Copy",
				"dependsOn": [],
				"policy": {
					"timeout": "0.12:00:00",
					"retry": 0,
					"retryIntervalInSeconds": 30,
					"secureOutput": false,
					"secureInput": false
				},
				"userProperties": [],
				"typeProperties": {
					"source": {
						"type": "AzureSqlSource",
						"sqlReaderStoredProcedureName": "[dbo].[cust_sale]",
						"storedProcedureParameters": {
							"enddate": {
								"type": "String",
								"value": {
									"value": "@pipeline().parameters.pendate",
									"type": "Expression"
								}
							},
							"startdate": {
								"type": "String",
								"value": {
									"value": "@pipeline().parameters.pstartdate",
									"type": "Expression"
								}
							}
						},
						"queryTimeout": "02:00:00",
						"partitionOption": "None"
					},
					"sink": {
						"type": "ParquetSink",
						"storeSettings": {
							"type": "AzureBlobFSWriteSettings"
						},
						"formatSettings": {
							"type": "ParquetWriteSettings"
						}
					},
					"enableStaging": false
				},
				"inputs": [
					{
						"referenceName": "db_ls",
						"type": "DatasetReference"
					}
				]
			}
		],
		"parameters": {
			"pendate": {
				"type": "string"
			},
			"pstartdate": {
				"type": "string"
			}
		},
		"annotations": []
	}
}